docs/conf.py
examples/basic_economics.py
examples/basic_fit_forecast.py
examples/basic_segmented.py
examples/integration_timesmith.py
ressmith/__init__.py
ressmith/objects/__init__.py
ressmith/objects/domain.py
ressmith/objects/validate.py
ressmith/primitives/__init__.py
ressmith/primitives/advanced_decline.py
ressmith/primitives/base.py
ressmith/primitives/constraints.py
ressmith/primitives/data_utils.py
ressmith/primitives/decline.py
ressmith/primitives/diagnostics.py
ressmith/primitives/economics.py
ressmith/primitives/ensemble.py
ressmith/primitives/fitting_utils.py
ressmith/primitives/models.py
ressmith/primitives/preprocessing.py
ressmith/primitives/reserves.py
ressmith/primitives/segmented.py
ressmith/primitives/switch.py
ressmith/primitives/uncertainty.py
ressmith/primitives/variants.py
ressmith/primitives/yields.py
ressmith/tasks/__init__.py
ressmith/tasks/core.py
ressmith/workflows/__init__.py
ressmith/workflows/analysis.py
ressmith/workflows/backtesting.py
ressmith/workflows/core.py
ressmith/workflows/ensemble.py
ressmith/workflows/integrations.py
ressmith/workflows/io.py
ressmith/workflows/multiphase.py
ressmith/workflows/portfolio.py
ressmith/workflows/scenarios.py
ressmith/workflows/uncertainty.py
ressmith-0.2.1.dist-info/licenses/LICENSE
scripts/smoke.py
tests/__init__.py
tests/test_integration_timesmith.py
tests/test_objects_validate.py
tests/test_primitives_advanced_models.py
tests/test_primitives_decline.py
tests/test_primitives_diagnostics.py
tests/test_primitives_economics.py
tests/test_primitives_ensemble.py
tests/test_primitives_preprocessing.py
tests/test_primitives_segmented.py
tests/test_primitives_variants.py
tests/test_workflows.py
tests/test_workflows_backtesting.py
tests/test_workflows_ensemble.py
tests/test_workflows_multiphase.py
tests/test_workflows_portfolio.py
tests/test_workflows_scenarios.py
ressmith-0.2.1.dist-info/METADATA
ressmith-0.2.1.dist-info/WHEEL
ressmith-0.2.1.dist-info/entry_points.txt
ressmith-0.2.1.dist-info/top_level.txt
ressmith-0.2.1.dist-info/RECORD
