Metadata-Version: 2.4
Name: ressmith
Version: 0.2.1
Summary: Reservoir decline curve analysis and forecasting for production optimization and economic evaluation
Author-email: "Kyle T. Jones" <kyletjones@gmail.com>
Maintainer-email: "Kyle T. Jones" <kyletjones@gmail.com>
License-Expression: MIT
Project-URL: Homepage, https://github.com/kylejones200/ressmith
Project-URL: Documentation, https://ressmith.readthedocs.io/
Project-URL: Repository, https://github.com/kylejones200/ressmith
Project-URL: Bug Tracker, https://github.com/kylejones200/ressmith/issues
Project-URL: Changelog, https://github.com/kylejones200/ressmith/blob/main/CHANGELOG.md
Requires-Python: >=3.12
License-File: LICENSE
Requires-Dist: numpy>=1.24.0
Requires-Dist: pandas>=2.0.0
Requires-Dist: timesmith>=0.1.0
Provides-Extra: fit
Requires-Dist: scipy>=1.10.0; extra == "fit"
Provides-Extra: viz
Requires-Dist: matplotlib>=3.7.0; extra == "viz"
Provides-Extra: dev
Requires-Dist: pytest>=7.0; extra == "dev"
Requires-Dist: pytest-cov>=4.0; extra == "dev"
Requires-Dist: ruff>=0.1.0; extra == "dev"
Requires-Dist: black>=23.0.0; extra == "dev"
Requires-Dist: mypy>=1.0.0; extra == "dev"
Provides-Extra: docs
Requires-Dist: sphinx>=7.0; extra == "docs"
Requires-Dist: sphinx-rtd-theme>=2.0; extra == "docs"
Requires-Dist: sphinx-autodoc-typehints>=1.20; extra == "docs"
Provides-Extra: examples
Requires-Dist: jupyter>=1.0; extra == "examples"
Requires-Dist: notebook>=7.0; extra == "examples"
Requires-Dist: ipykernel>=6.0; extra == "examples"
Provides-Extra: all
Requires-Dist: ressmith[dev,docs,examples,fit,viz]; extra == "all"
Dynamic: license-file
